netbox_autonames/__init__.py
netbox_autonames/forms.py
netbox_autonames/signals.py
netbox_autonames-0.4.2.dist-info/LICENSE
netbox_autonames-0.4.2.dist-info/METADATA
netbox_autonames-0.4.2.dist-info/WHEEL
netbox_autonames-0.4.2.dist-info/top_level.txt
netbox_autonames-0.4.2.dist-info/RECORD
