Metadata-Version: 2.1
Name: netbox_autonames
Version: 0.4.2
Summary: Auto-generate names for devices in NetBox based on their role.
Home-page: https://github.com/jaannnis/netbox_autonames
Author: jannis
License: AGPLv3
License-File: LICENSE
